{
 "ETag": "W/\"3aaea36460dde9b2cdd5eb1ca4e606bfed39da75222bcb07b812aa4d4b3d2f15\"",
 "Last-Modified": "Thu, 30 Sep 2021 21:02:23 GMT",
 "base": {
  "repo": {
   "name": "transfocate-feedstock"
  }
 },
 "closed_at": "2021-09-30T21:02:22Z",
 "created_at": "2021-09-30T20:46:58Z",
 "draft": false,
 "head": {
  "ref": "this_is_not_a_branch"
 },
 "html_url": "https://github.com/conda-forge/transfocate-feedstock/pull/4",
 "id": 747036543,
 "labels": [],
 "mergeable": null,
 "mergeable_state": "unknown",
 "merged": true,
 "merged_at": "2021-09-30T21:02:22Z",
 "number": 4,
 "state": "closed",
 "updated_at": "2021-09-30T21:02:23Z"
}