{
 "ETag": "W/\"dfffe9e66075f00214329cddc45e58362ead267d62c8d6ab722464e396c37abf\"",
 "Last-Modified": "Fri, 09 Dec 2022 21:43:03 GMT",
 "base": {
  "repo": {
   "name": "mailchecker-feedstock"
  }
 },
 "closed_at": "2022-12-09T21:42:59Z",
 "created_at": "2022-12-09T21:37:04Z",
 "draft": false,
 "head": {
  "ref": "this_is_not_a_branch"
 },
 "html_url": "https://github.com/conda-forge/mailchecker-feedstock/pull/45",
 "id": 1156715389,
 "labels": [],
 "mergeable": null,
 "mergeable_state": "unknown",
 "merged": true,
 "merged_at": "2022-12-09T21:42:59Z",
 "number": 45,
 "state": "closed",
 "updated_at": "2022-12-09T21:43:03Z"
}