{
 "archived": false,
 "branch": "main",
 "conda-forge.yml": {
  "build_platform": {
   "linux_aarch64": "linux_64",
   "osx_arm64": "osx_64"
  },
  "conda_build": {
   "pkg_format": "2"
  },
  "conda_forge_output_validation": true,
  "github": {
   "branch_name": "main",
   "tooling_branch_name": "main"
  },
  "provider": {
   "linux_aarch64": "default"
  },
  "test_on_native_only": true
 },
 "feedstock_name": "r-tiledb",
 "hash_type": "sha256",
 "linux_64_meta_yaml": {
  "about": {
   "description": "TileDB is a highly-parallelized, cloud native array storage engine.\n",
   "dev_url": "https://github.com/TileDB-Inc/TileDB-R",
   "doc_url": "https://docs.tiledb.com/developer/",
   "home": "https://www.tiledb.com",
   "license": "MIT",
   "license_file": [
    "/lib/R/share/licenses/MIT",
    "LICENSE",
    "/lib/R/share/licenses/MIT",
    "LICENSE"
   ],
   "summary": "R interface to the TileDB array storage manager"
  },
  "build": {
   "number": "0",
   "rpaths": [
    "lib/R/lib/",
    "lib/",
    "lib/R/lib/",
    "lib/"
   ]
  },
  "extra": {
   "recipe-maintainers": [
    "ihnorton",
    "Shelnutt2",
    "eddelbuettel",
    "jdblischak",
    "ihnorton",
    "Shelnutt2",
    "eddelbuettel",
    "jdblischak"
   ]
  },
  "package": {
   "name": "r-tiledb",
   "version": "0.23.0"
  },
  "requirements": {
   "build": [
    "cxx_compiler_stub",
    "pkg-config",
    "make",
    "cxx_compiler_stub",
    "pkg-config",
    "make"
   ],
   "host": [
    "r-base",
    "tiledb 2.19.*",
    "r-rcpp >=1.0.8",
    "r-rcppspdlog",
    "r-nanotime",
    "r-spdl",
    "r-rcppint64",
    "r-base",
    "tiledb 2.19.*",
    "r-rcpp >=1.0.8",
    "r-rcppspdlog",
    "r-nanotime",
    "r-spdl",
    "r-rcppint64"
   ],
   "run": [
    "r-base",
    "r-nanotime",
    "tiledb 2.19.*",
    "r-spdl",
    "r-base",
    "r-nanotime",
    "tiledb 2.19.*",
    "r-spdl"
   ]
  },
  "source": {
   "sha256": "28ff34932b29a37650794af67aa6d336c1e3440c50cbc64940ff9f01098289df",
   "url": "https://github.com/TileDB-Inc/TileDB-R/archive/0.23.0.tar.gz"
  },
  "test": {
   "commands": [
    "Rscript -e 'tinytest::test_package(\"tiledb\")'",
    "Rscript -e 'tinytest::test_package(\"tiledb\")'"
   ],
   "requires": [
    "r-tinytest",
    "r-nycflights13",
    "r-palmerpenguins",
    "r-data.table",
    "r-tinytest",
    "r-nycflights13",
    "r-palmerpenguins",
    "r-data.table"
   ]
  }
 },
 "linux_64_requirements": {
  "build": {
   "__set__": true,
   "elements": [
    "cxx_compiler_stub",
    "make",
    "pkg-config"
   ]
  },
  "host": {
   "__set__": true,
   "elements": [
    "r-base",
    "r-nanotime",
    "r-rcpp",
    "r-rcppint64",
    "r-rcppspdlog",
    "r-spdl",
    "tiledb"
   ]
  },
  "run": {
   "__set__": true,
   "elements": [
    "r-base",
    "r-nanotime",
    "r-spdl",
    "tiledb"
   ]
  },
  "test": {
   "__set__": true,
   "elements": [
    "r-data.table",
    "r-nycflights13",
    "r-palmerpenguins",
    "r-tinytest"
   ]
  }
 },
 "linux_aarch64_meta_yaml": {
  "about": {
   "description": "TileDB is a highly-parallelized, cloud native array storage engine.\n",
   "dev_url": "https://github.com/TileDB-Inc/TileDB-R",
   "doc_url": "https://docs.tiledb.com/developer/",
   "home": "https://www.tiledb.com",
   "license": "MIT",
   "license_file": [
    "/lib/R/share/licenses/MIT",
    "LICENSE",
    "/lib/R/share/licenses/MIT",
    "LICENSE"
   ],
   "summary": "R interface to the TileDB array storage manager"
  },
  "build": {
   "number": "0",
   "rpaths": [
    "lib/R/lib/",
    "lib/",
    "lib/R/lib/",
    "lib/"
   ]
  },
  "extra": {
   "recipe-maintainers": [
    "ihnorton",
    "Shelnutt2",
    "eddelbuettel",
    "jdblischak",
    "ihnorton",
    "Shelnutt2",
    "eddelbuettel",
    "jdblischak"
   ]
  },
  "package": {
   "name": "r-tiledb",
   "version": "0.23.0"
  },
  "requirements": {
   "build": [
    "cxx_compiler_stub",
    "pkg-config",
    "make",
    "cxx_compiler_stub",
    "pkg-config",
    "make"
   ],
   "host": [
    "r-base",
    "tiledb 2.19.*",
    "r-rcpp >=1.0.8",
    "r-rcppspdlog",
    "r-nanotime",
    "r-spdl",
    "r-rcppint64",
    "r-base",
    "tiledb 2.19.*",
    "r-rcpp >=1.0.8",
    "r-rcppspdlog",
    "r-nanotime",
    "r-spdl",
    "r-rcppint64"
   ],
   "run": [
    "r-base",
    "r-nanotime",
    "tiledb 2.19.*",
    "r-spdl",
    "r-base",
    "r-nanotime",
    "tiledb 2.19.*",
    "r-spdl"
   ]
  },
  "source": {
   "sha256": "28ff34932b29a37650794af67aa6d336c1e3440c50cbc64940ff9f01098289df",
   "url": "https://github.com/TileDB-Inc/TileDB-R/archive/0.23.0.tar.gz"
  },
  "test": {
   "commands": [
    "Rscript -e 'tinytest::test_package(\"tiledb\")'",
    "Rscript -e 'tinytest::test_package(\"tiledb\")'"
   ],
   "requires": [
    "r-tinytest",
    "r-nycflights13",
    "r-palmerpenguins",
    "r-data.table",
    "r-tinytest",
    "r-nycflights13",
    "r-palmerpenguins",
    "r-data.table"
   ]
  }
 },
 "linux_aarch64_requirements": {
  "build": {
   "__set__": true,
   "elements": [
    "cxx_compiler_stub",
    "make",
    "pkg-config"
   ]
  },
  "host": {
   "__set__": true,
   "elements": [
    "r-base",
    "r-nanotime",
    "r-rcpp",
    "r-rcppint64",
    "r-rcppspdlog",
    "r-spdl",
    "tiledb"
   ]
  },
  "run": {
   "__set__": true,
   "elements": [
    "r-base",
    "r-nanotime",
    "r-spdl",
    "tiledb"
   ]
  },
  "test": {
   "__set__": true,
   "elements": [
    "r-data.table",
    "r-nycflights13",
    "r-palmerpenguins",
    "r-tinytest"
   ]
  }
 },
 "meta_yaml": {
  "about": {
   "description": "TileDB is a highly-parallelized, cloud native array storage engine.\n",
   "dev_url": "https://github.com/TileDB-Inc/TileDB-R",
   "doc_url": "https://docs.tiledb.com/developer/",
   "home": "https://www.tiledb.com",
   "license": "MIT",
   "license_file": [
    "/lib/R/share/licenses/MIT",
    "LICENSE",
    "/lib/R/share/licenses/MIT",
    "LICENSE",
    "/lib/R/share/licenses/MIT",
    "LICENSE",
    "/lib/R/share/licenses/MIT",
    "LICENSE",
    "/lib/R/share/licenses/MIT",
    "LICENSE",
    "/lib/R/share/licenses/MIT",
    "LICENSE",
    "/lib/R/share/licenses/MIT",
    "LICENSE",
    "/lib/R/share/licenses/MIT",
    "LICENSE"
   ],
   "summary": "R interface to the TileDB array storage manager"
  },
  "build": {
   "number": "0",
   "rpaths": [
    "lib/R/lib/",
    "lib/",
    "lib/R/lib/",
    "lib/",
    "lib/R/lib/",
    "lib/",
    "lib/R/lib/",
    "lib/",
    "lib/R/lib/",
    "lib/",
    "lib/R/lib/",
    "lib/",
    "lib/R/lib/",
    "lib/",
    "lib/R/lib/",
    "lib/"
   ]
  },
  "extra": {
   "recipe-maintainers": [
    "ihnorton",
    "Shelnutt2",
    "eddelbuettel",
    "jdblischak",
    "ihnorton",
    "Shelnutt2",
    "eddelbuettel",
    "jdblischak",
    "ihnorton",
    "Shelnutt2",
    "eddelbuettel",
    "jdblischak",
    "ihnorton",
    "Shelnutt2",
    "eddelbuettel",
    "jdblischak",
    "ihnorton",
    "Shelnutt2",
    "eddelbuettel",
    "jdblischak",
    "ihnorton",
    "Shelnutt2",
    "eddelbuettel",
    "jdblischak",
    "ihnorton",
    "Shelnutt2",
    "eddelbuettel",
    "jdblischak",
    "ihnorton",
    "Shelnutt2",
    "eddelbuettel",
    "jdblischak"
   ]
  },
  "package": {
   "name": "r-tiledb",
   "version": "0.23.0"
  },
  "requirements": {
   "build": [
    "cxx_compiler_stub",
    "pkg-config",
    "make",
    "cxx_compiler_stub",
    "pkg-config",
    "make",
    "cxx_compiler_stub",
    "pkg-config",
    "make",
    "cxx_compiler_stub",
    "pkg-config",
    "make",
    "cxx_compiler_stub",
    "pkg-config",
    "make",
    "cxx_compiler_stub",
    "pkg-config",
    "make",
    "cxx_compiler_stub",
    "pkg-config",
    "make",
    "cxx_compiler_stub",
    "pkg-config",
    "make"
   ],
   "host": [
    "r-base",
    "tiledb 2.19.*",
    "r-rcpp >=1.0.8",
    "r-rcppspdlog",
    "r-nanotime",
    "r-spdl",
    "r-rcppint64",
    "r-base",
    "tiledb 2.19.*",
    "r-rcpp >=1.0.8",
    "r-rcppspdlog",
    "r-nanotime",
    "r-spdl",
    "r-rcppint64",
    "r-base",
    "tiledb 2.19.*",
    "r-rcpp >=1.0.8",
    "r-rcppspdlog",
    "r-nanotime",
    "r-spdl",
    "r-rcppint64",
    "r-base",
    "tiledb 2.19.*",
    "r-rcpp >=1.0.8",
    "r-rcppspdlog",
    "r-nanotime",
    "r-spdl",
    "r-rcppint64",
    "r-base",
    "tiledb 2.19.*",
    "r-rcpp >=1.0.8",
    "r-rcppspdlog",
    "r-nanotime",
    "r-spdl",
    "r-rcppint64",
    "r-base",
    "tiledb 2.19.*",
    "r-rcpp >=1.0.8",
    "r-rcppspdlog",
    "r-nanotime",
    "r-spdl",
    "r-rcppint64",
    "r-base",
    "tiledb 2.19.*",
    "r-rcpp >=1.0.8",
    "r-rcppspdlog",
    "r-nanotime",
    "r-spdl",
    "r-rcppint64",
    "r-base",
    "tiledb 2.19.*",
    "r-rcpp >=1.0.8",
    "r-rcppspdlog",
    "r-nanotime",
    "r-spdl",
    "r-rcppint64"
   ],
   "run": [
    "r-base",
    "r-nanotime",
    "tiledb 2.19.*",
    "r-spdl",
    "r-base",
    "r-nanotime",
    "tiledb 2.19.*",
    "r-spdl",
    "r-base",
    "r-nanotime",
    "tiledb 2.19.*",
    "r-spdl",
    "r-base",
    "r-nanotime",
    "tiledb 2.19.*",
    "r-spdl",
    "r-base",
    "r-nanotime",
    "tiledb 2.19.*",
    "r-spdl",
    "r-base",
    "r-nanotime",
    "tiledb 2.19.*",
    "r-spdl",
    "r-base",
    "r-nanotime",
    "tiledb 2.19.*",
    "r-spdl",
    "r-base",
    "r-nanotime",
    "tiledb 2.19.*",
    "r-spdl"
   ]
  },
  "source": {
   "patches": [
    "0001-skip-osx-test-to-avoid-spurious-segfault.patch",
    "0001-skip-osx-test-to-avoid-spurious-segfault.patch"
   ],
   "sha256": "28ff34932b29a37650794af67aa6d336c1e3440c50cbc64940ff9f01098289df",
   "url": "https://github.com/TileDB-Inc/TileDB-R/archive/0.23.0.tar.gz"
  },
  "test": {
   "commands": [
    "Rscript -e 'tinytest::test_package(\"tiledb\")'",
    "Rscript -e 'tinytest::test_package(\"tiledb\")'",
    "Rscript -e 'tinytest::test_package(\"tiledb\")'",
    "Rscript -e 'tinytest::test_package(\"tiledb\")'",
    "Rscript -e 'tinytest::test_package(\"tiledb\")'",
    "Rscript -e 'tinytest::test_package(\"tiledb\")'",
    "Rscript -e 'tinytest::test_package(\"tiledb\")'",
    "Rscript -e 'tinytest::test_package(\"tiledb\")'"
   ],
   "requires": [
    "r-tinytest",
    "r-nycflights13",
    "r-palmerpenguins",
    "r-data.table",
    "r-tinytest",
    "r-nycflights13",
    "r-palmerpenguins",
    "r-data.table",
    "r-tinytest",
    "r-nycflights13",
    "r-palmerpenguins",
    "r-data.table",
    "r-tinytest",
    "r-nycflights13",
    "r-palmerpenguins",
    "r-data.table",
    "r-tinytest",
    "r-nycflights13",
    "r-palmerpenguins",
    "r-data.table",
    "r-tinytest",
    "r-nycflights13",
    "r-palmerpenguins",
    "r-data.table",
    "r-tinytest",
    "r-nycflights13",
    "r-palmerpenguins",
    "r-data.table",
    "r-tinytest",
    "r-nycflights13",
    "r-palmerpenguins",
    "r-data.table"
   ]
  }
 },
 "name": "r-tiledb",
 "osx_64_meta_yaml": {
  "about": {
   "description": "TileDB is a highly-parallelized, cloud native array storage engine.\n",
   "dev_url": "https://github.com/TileDB-Inc/TileDB-R",
   "doc_url": "https://docs.tiledb.com/developer/",
   "home": "https://www.tiledb.com",
   "license": "MIT",
   "license_file": [
    "/lib/R/share/licenses/MIT",
    "LICENSE",
    "/lib/R/share/licenses/MIT",
    "LICENSE"
   ],
   "summary": "R interface to the TileDB array storage manager"
  },
  "build": {
   "number": "0",
   "rpaths": [
    "lib/R/lib/",
    "lib/",
    "lib/R/lib/",
    "lib/"
   ]
  },
  "extra": {
   "recipe-maintainers": [
    "ihnorton",
    "Shelnutt2",
    "eddelbuettel",
    "jdblischak",
    "ihnorton",
    "Shelnutt2",
    "eddelbuettel",
    "jdblischak"
   ]
  },
  "package": {
   "name": "r-tiledb",
   "version": "0.23.0"
  },
  "requirements": {
   "build": [
    "cxx_compiler_stub",
    "pkg-config",
    "make",
    "cxx_compiler_stub",
    "pkg-config",
    "make"
   ],
   "host": [
    "r-base",
    "tiledb 2.19.*",
    "r-rcpp >=1.0.8",
    "r-rcppspdlog",
    "r-nanotime",
    "r-spdl",
    "r-rcppint64",
    "r-base",
    "tiledb 2.19.*",
    "r-rcpp >=1.0.8",
    "r-rcppspdlog",
    "r-nanotime",
    "r-spdl",
    "r-rcppint64"
   ],
   "run": [
    "r-base",
    "r-nanotime",
    "tiledb 2.19.*",
    "r-spdl",
    "r-base",
    "r-nanotime",
    "tiledb 2.19.*",
    "r-spdl"
   ]
  },
  "source": {
   "patches": [
    "0001-skip-osx-test-to-avoid-spurious-segfault.patch",
    "0001-skip-osx-test-to-avoid-spurious-segfault.patch"
   ],
   "sha256": "28ff34932b29a37650794af67aa6d336c1e3440c50cbc64940ff9f01098289df",
   "url": "https://github.com/TileDB-Inc/TileDB-R/archive/0.23.0.tar.gz"
  },
  "test": {
   "commands": [
    "Rscript -e 'tinytest::test_package(\"tiledb\")'",
    "Rscript -e 'tinytest::test_package(\"tiledb\")'"
   ],
   "requires": [
    "r-tinytest",
    "r-nycflights13",
    "r-palmerpenguins",
    "r-data.table",
    "r-tinytest",
    "r-nycflights13",
    "r-palmerpenguins",
    "r-data.table"
   ]
  }
 },
 "osx_64_requirements": {
  "build": {
   "__set__": true,
   "elements": [
    "cxx_compiler_stub",
    "make",
    "pkg-config"
   ]
  },
  "host": {
   "__set__": true,
   "elements": [
    "r-base",
    "r-nanotime",
    "r-rcpp",
    "r-rcppint64",
    "r-rcppspdlog",
    "r-spdl",
    "tiledb"
   ]
  },
  "run": {
   "__set__": true,
   "elements": [
    "r-base",
    "r-nanotime",
    "r-spdl",
    "tiledb"
   ]
  },
  "test": {
   "__set__": true,
   "elements": [
    "r-data.table",
    "r-nycflights13",
    "r-palmerpenguins",
    "r-tinytest"
   ]
  }
 },
 "osx_arm64_meta_yaml": {
  "about": {
   "description": "TileDB is a highly-parallelized, cloud native array storage engine.\n",
   "dev_url": "https://github.com/TileDB-Inc/TileDB-R",
   "doc_url": "https://docs.tiledb.com/developer/",
   "home": "https://www.tiledb.com",
   "license": "MIT",
   "license_file": [
    "/lib/R/share/licenses/MIT",
    "LICENSE",
    "/lib/R/share/licenses/MIT",
    "LICENSE"
   ],
   "summary": "R interface to the TileDB array storage manager"
  },
  "build": {
   "number": "0",
   "rpaths": [
    "lib/R/lib/",
    "lib/",
    "lib/R/lib/",
    "lib/"
   ]
  },
  "extra": {
   "recipe-maintainers": [
    "ihnorton",
    "Shelnutt2",
    "eddelbuettel",
    "jdblischak",
    "ihnorton",
    "Shelnutt2",
    "eddelbuettel",
    "jdblischak"
   ]
  },
  "package": {
   "name": "r-tiledb",
   "version": "0.23.0"
  },
  "requirements": {
   "build": [
    "cxx_compiler_stub",
    "pkg-config",
    "make",
    "cxx_compiler_stub",
    "pkg-config",
    "make"
   ],
   "host": [
    "r-base",
    "tiledb 2.19.*",
    "r-rcpp >=1.0.8",
    "r-rcppspdlog",
    "r-nanotime",
    "r-spdl",
    "r-rcppint64",
    "r-base",
    "tiledb 2.19.*",
    "r-rcpp >=1.0.8",
    "r-rcppspdlog",
    "r-nanotime",
    "r-spdl",
    "r-rcppint64"
   ],
   "run": [
    "r-base",
    "r-nanotime",
    "tiledb 2.19.*",
    "r-spdl",
    "r-base",
    "r-nanotime",
    "tiledb 2.19.*",
    "r-spdl"
   ]
  },
  "source": {
   "sha256": "28ff34932b29a37650794af67aa6d336c1e3440c50cbc64940ff9f01098289df",
   "url": "https://github.com/TileDB-Inc/TileDB-R/archive/0.23.0.tar.gz"
  },
  "test": {
   "commands": [
    "Rscript -e 'tinytest::test_package(\"tiledb\")'",
    "Rscript -e 'tinytest::test_package(\"tiledb\")'"
   ],
   "requires": [
    "r-tinytest",
    "r-nycflights13",
    "r-palmerpenguins",
    "r-data.table",
    "r-tinytest",
    "r-nycflights13",
    "r-palmerpenguins",
    "r-data.table"
   ]
  }
 },
 "osx_arm64_requirements": {
  "build": {
   "__set__": true,
   "elements": [
    "cxx_compiler_stub",
    "make",
    "pkg-config"
   ]
  },
  "host": {
   "__set__": true,
   "elements": [
    "r-base",
    "r-nanotime",
    "r-rcpp",
    "r-rcppint64",
    "r-rcppspdlog",
    "r-spdl",
    "tiledb"
   ]
  },
  "run": {
   "__set__": true,
   "elements": [
    "r-base",
    "r-nanotime",
    "r-spdl",
    "tiledb"
   ]
  },
  "test": {
   "__set__": true,
   "elements": [
    "r-data.table",
    "r-nycflights13",
    "r-palmerpenguins",
    "r-tinytest"
   ]
  }
 },
 "outputs_names": {
  "__set__": true,
  "elements": [
   "r-tiledb"
  ]
 },
 "parsing_error": false,
 "platforms": [
  "linux_64",
  "linux_aarch64",
  "osx_64",
  "osx_arm64"
 ],
 "pr_info": {
  "__lazy_json__": "pr_info/r-tiledb.json"
 },
 "raw_meta_yaml": "{% set name = \"r-tiledb\" %}\n{% set version = \"0.23.0\" %}\n\npackage:\n  name: {{ name|lower }}\n  version: {{ version }}\n\nsource:\n  url: https://github.com/TileDB-Inc/TileDB-R/archive/{{ version }}.tar.gz\n  sha256: 28ff34932b29a37650794af67aa6d336c1e3440c50cbc64940ff9f01098289df\n  patches:   # [osx and not arm64]\n    - 0001-skip-osx-test-to-avoid-spurious-segfault.patch  # [osx and not arm64]\n\nbuild:\n  number: 0\n  skip: true  # [win]\n  rpaths:\n    - lib/R/lib/\n    - lib/\n\nrequirements:\n  build:\n    - {{ compiler('cxx') }}\n    - pkg-config\n    - make\n    - cross-r-base {{ r_base }}  # [build_platform != target_platform]\n    - r-nanotime  # [build_platform != target_platform]\n    - r-rcpp >=1.0.8  # [build_platform != target_platform]\n    - r-rcppspdlog  # [build_platform != target_platform]\n    - r-rcppint64  # [build_platform != target_platform]\n  host:\n    - r-base\n    - tiledb 2.19.*\n    - r-rcpp >=1.0.8\n    - r-rcppspdlog\n    - r-nanotime\n    - r-spdl\n    - r-rcppint64\n  run:\n    - r-base\n    - r-nanotime\n    - tiledb 2.19.*\n    - r-spdl\n\ntest:\n  requires:\n    - r-tinytest\n    - r-nycflights13\n    - r-palmerpenguins\n    - r-data.table\n  commands:\n    - Rscript -e 'tinytest::test_package(\"tiledb\")'\n\nabout:\n  home: https://www.tiledb.com\n  license: MIT\n  license_file:\n    - {{ environ[\"PREFIX\"] }}/lib/R/share/licenses/MIT\n    - LICENSE\n  summary: R interface to the TileDB array storage manager\n\n  description: |\n    TileDB is a highly-parallelized, cloud native array storage engine.\n  doc_url: https://docs.tiledb.com/developer/\n  dev_url: https://github.com/TileDB-Inc/TileDB-R\n\nextra:\n  recipe-maintainers:\n    - ihnorton\n    - Shelnutt2\n    - eddelbuettel\n    - jdblischak\n",
 "req": {
  "__set__": true,
  "elements": [
   "cxx_compiler_stub",
   "make",
   "pkg-config",
   "r-base",
   "r-nanotime",
   "r-rcpp",
   "r-rcppint64",
   "r-rcppspdlog",
   "r-spdl",
   "tiledb"
  ]
 },
 "requirements": {
  "build": {
   "__set__": true,
   "elements": [
    "cxx_compiler_stub",
    "make",
    "pkg-config"
   ]
  },
  "host": {
   "__set__": true,
   "elements": [
    "cxx_compiler_stub",
    "r-base",
    "r-nanotime",
    "r-rcpp",
    "r-rcppint64",
    "r-rcppspdlog",
    "r-spdl",
    "tiledb"
   ]
  },
  "run": {
   "__set__": true,
   "elements": [
    "cxx_compiler_stub",
    "r-base",
    "r-nanotime",
    "r-spdl",
    "tiledb"
   ]
  },
  "test": {
   "__set__": true,
   "elements": [
    "r-data.table",
    "r-nycflights13",
    "r-palmerpenguins",
    "r-tinytest"
   ]
  }
 },
 "strong_exports": false,
 "total_requirements": {
  "build": {
   "__set__": true,
   "elements": [
    "cxx_compiler_stub",
    "make",
    "pkg-config"
   ]
  },
  "host": {
   "__set__": true,
   "elements": [
    "r-base",
    "r-nanotime",
    "r-rcpp >=1.0.8",
    "r-rcppint64",
    "r-rcppspdlog",
    "r-spdl",
    "tiledb 2.19.*"
   ]
  },
  "run": {
   "__set__": true,
   "elements": [
    "r-base",
    "r-nanotime",
    "r-spdl",
    "tiledb 2.19.*"
   ]
  },
  "test": {
   "__set__": true,
   "elements": [
    "r-data.table",
    "r-nycflights13",
    "r-palmerpenguins",
    "r-tinytest"
   ]
  }
 },
 "url": "https://github.com/TileDB-Inc/TileDB-R/archive/0.23.0.tar.gz",
 "version": "0.23.0",
 "version_pr_info": {
  "__lazy_json__": "version_pr_info/r-tiledb.json"
 }
}