{
 "ETag": "W/\"1ecc1ebb4e0188994f00e200e1fe760281ad7d11c3b65ed6472e096838f0e2b3\"",
 "Last-Modified": "Mon, 03 Oct 2022 14:10:45 GMT",
 "base": {
  "repo": {
   "name": "redmail-feedstock"
  }
 },
 "closed_at": "2022-10-03T14:10:44Z",
 "created_at": "2022-10-01T23:25:32Z",
 "draft": false,
 "head": {
  "ref": "this_is_not_a_branch"
 },
 "html_url": "https://github.com/conda-forge/redmail-feedstock/pull/6",
 "id": 1073702525,
 "labels": [],
 "mergeable": null,
 "mergeable_state": "unknown",
 "merged": true,
 "merged_at": "2022-10-03T14:10:44Z",
 "number": 6,
 "state": "closed",
 "updated_at": "2022-10-03T14:10:45Z"
}