{
 "ETag": "W/\"ef47befc1a470efd724e19c0ee222a3e57c4bb69f1f02a2d02ed2f1ed32f14f7\"",
 "Last-Modified": "Sat, 01 Oct 2022 23:08:22 GMT",
 "base": {
  "repo": {
   "name": "apache-airflow-providers-jdbc-feedstock"
  }
 },
 "closed_at": "2022-10-01T23:08:22Z",
 "created_at": "2022-10-01T17:18:28Z",
 "draft": false,
 "head": {
  "ref": "this_is_not_a_branch"
 },
 "html_url": "https://github.com/conda-forge/apache-airflow-providers-jdbc-feedstock/pull/10",
 "id": 1073618291,
 "labels": [],
 "mergeable": null,
 "mergeable_state": "unknown",
 "merged": true,
 "merged_at": "2022-10-01T23:08:22Z",
 "number": 10,
 "state": "closed",
 "updated_at": "2022-10-01T23:08:22Z"
}