{
 "ETag": "W/\"56544628a4f80813c3118d96026a7bc5ad13f0d00c71798d77380bcb44997acb\"",
 "Last-Modified": "Thu, 19 Aug 2021 21:13:56 GMT",
 "base": {
  "repo": {
   "name": "types-deprecated-feedstock"
  }
 },
 "closed_at": "2021-08-19T21:13:56Z",
 "created_at": "2021-08-19T20:36:03Z",
 "draft": false,
 "head": {
  "ref": "this_is_not_a_branch"
 },
 "html_url": "https://github.com/conda-forge/types-deprecated-feedstock/pull/2",
 "id": 716244604,
 "labels": [],
 "mergeable": null,
 "mergeable_state": "unknown",
 "merged": true,
 "merged_at": "2021-08-19T21:13:55Z",
 "number": 2,
 "state": "closed",
 "updated_at": "2021-08-19T21:13:56Z"
}