{
 "ETag": "W/\"5abe949479dfdd3fd4bf0906ef617e9e7d06339c4e49cefbaeb61d565f26f641\"",
 "Last-Modified": "Thu, 20 May 2021 15:35:57 GMT",
 "base": {
  "repo": {
   "name": "sirius-feedstock"
  }
 },
 "closed_at": "2021-05-20T15:35:56Z",
 "created_at": "2021-05-20T14:54:40Z",
 "draft": false,
 "head": {
  "ref": "this_is_not_a_branch"
 },
 "html_url": "https://github.com/conda-forge/sirius-feedstock/pull/2",
 "id": 648990287,
 "labels": [],
 "mergeable": null,
 "mergeable_state": "unknown",
 "merged": true,
 "merged_at": "2021-05-20T15:35:56Z",
 "number": 2,
 "state": "closed",
 "updated_at": "2021-05-20T15:35:57Z"
}