{
 "ETag": "W/\"e706bfe66c502c30500a4c115060633b3331a4a56da1e350d75cb209edbf65c4\"",
 "Last-Modified": "Tue, 20 Oct 2020 17:21:06 GMT",
 "base": {
  "repo": {
   "name": "clingo-feedstock"
  }
 },
 "closed_at": "2020-10-20T17:21:05Z",
 "created_at": "2020-03-20T23:57:57Z",
 "draft": false,
 "head": {
  "ref": "rebuild-pypy-0-1"
 },
 "html_url": "https://github.com/conda-forge/clingo-feedstock/pull/2",
 "id": 391784272,
 "labels": [
  {
   "color": "191970",
   "default": false,
   "description": "Instruct the bot to retry the PR",
   "id": 1,
   "name": "bot-rerun",
   "node_id": "hello",
   "url": "world"
  }
 ],
 "mergeable": false,
 "mergeable_state": "dirty",
 "merged": false,
 "merged_at": null,
 "number": 2,
 "state": "closed",
 "updated_at": "2020-10-20T17:21:06Z"
}