{
 "ETag": "W/\"d1731a8ce6e282bed8aedcb53845a063358e624c9f18e2eed8df814d1a60b3c3\"",
 "Last-Modified": "Tue, 17 Aug 2021 22:01:48 GMT",
 "base": {
  "repo": {
   "name": "mypy-boto3-s3-feedstock"
  }
 },
 "closed_at": "2021-08-17T22:01:45Z",
 "created_at": "2021-08-17T21:55:22Z",
 "draft": false,
 "head": {
  "ref": "this_is_not_a_branch"
 },
 "html_url": "https://github.com/conda-forge/mypy-boto3-s3-feedstock/pull/76",
 "id": 714591105,
 "labels": [],
 "mergeable": null,
 "mergeable_state": "unknown",
 "merged": true,
 "merged_at": "2021-08-17T22:01:45Z",
 "number": 76,
 "state": "closed",
 "updated_at": "2021-08-17T22:01:48Z"
}