{
 "ETag": "W/\"7d3f59d284082891af7511dce804a9ee\"",
 "Last-Modified": "Fri, 28 Feb 2020 12:29:56 GMT",
 "base": {
  "repo": {
   "name": "localstack-ext-feedstock"
  }
 },
 "closed_at": "2020-02-28T12:29:56Z",
 "created_at": "2020-02-28T08:23:43Z",
 "head": {
  "ref": "0.10.117"
 },
 "html_url": "https://github.com/conda-forge/localstack-ext-feedstock/pull/82",
 "id": 381264123,
 "labels": [],
 "mergeable": null,
 "mergeable_state": "unknown",
 "merged": true,
 "merged_at": "2020-02-28T12:29:56Z",
 "number": 82,
 "state": "closed",
 "updated_at": "2020-02-28T12:29:56Z"
}