{
 "ETag": "W/\"4254c6c4650417476bc2cbeec59a8967b103bbaae038b641d20ae33f2fe26503\"",
 "Last-Modified": "Mon, 30 May 2022 16:03:46 GMT",
 "base": {
  "repo": {
   "name": "cwinpy-feedstock"
  }
 },
 "closed_at": "2022-05-30T16:03:46Z",
 "created_at": "2022-01-19T17:08:32Z",
 "draft": false,
 "head": {
  "ref": "rebuild-python310-0-1_h6a9bac"
 },
 "html_url": "https://github.com/conda-forge/cwinpy-feedstock/pull/19",
 "id": 826723578,
 "labels": [
  {
   "color": "191970",
   "default": false,
   "description": "Instruct the bot to retry the PR",
   "id": 1,
   "name": "bot-rerun",
   "node_id": "hello",
   "url": "world"
  }
 ],
 "mergeable": false,
 "mergeable_state": "dirty",
 "merged": false,
 "merged_at": null,
 "number": 19,
 "state": "closed",
 "updated_at": "2022-05-30T16:03:46Z"
}