{
 "ETag": "W/\"15969ac4841fda301092e8607bc295b1ef2b184f464293a352b5e924afb9f5a6\"",
 "Last-Modified": "Sat, 30 Apr 2022 18:56:20 GMT",
 "base": {
  "repo": {
   "name": "reacnetgenerator-feedstock"
  }
 },
 "closed_at": "2022-04-30T18:56:20Z",
 "created_at": "2022-04-30T02:09:29Z",
 "draft": false,
 "head": {
  "ref": "1.5.1_hdbd313"
 },
 "html_url": "https://github.com/conda-forge/reacnetgenerator-feedstock/pull/66",
 "id": 924550222,
 "labels": [],
 "mergeable": null,
 "mergeable_state": "unknown",
 "merged": false,
 "merged_at": null,
 "number": 66,
 "state": "closed",
 "updated_at": "2022-04-30T18:56:20Z"
}