{
 "ETag": "W/\"df3cfac8bfe6e3734372852c9677475799c0d5d1329a2b2efc9dec241ec668dd\"",
 "Last-Modified": "Tue, 24 Oct 2023 11:00:12 GMT",
 "base": {
  "repo": {
   "name": "nordugrid-arc-feedstock"
  }
 },
 "closed_at": null,
 "created_at": "2023-10-24T11:00:06Z",
 "draft": false,
 "head": {
  "ref": "6.18.0_h24fff5"
 },
 "html_url": "https://github.com/conda-forge/nordugrid-arc-feedstock/pull/50",
 "id": 1570808144,
 "labels": [],
 "mergeable": true,
 "mergeable_state": "unstable",
 "merged": false,
 "merged_at": null,
 "number": 50,
 "state": "open",
 "updated_at": "2023-10-24T11:00:12Z"
}