{
 "ETag": "W/\"681d1b4fc7463be3f12d43a7049013395b86ca2db97474f9b276748f681ebe42\"",
 "Last-Modified": "Mon, 06 Dec 2021 18:01:56 GMT",
 "base": {
  "repo": {
   "name": "netcdf-cxx4-feedstock"
  }
 },
 "closed_at": "2021-12-06T18:01:56Z",
 "created_at": "2021-11-30T04:09:23Z",
 "draft": false,
 "head": {
  "ref": "bot-pr_arm_osx_h35d346"
 },
 "html_url": "https://github.com/conda-forge/netcdf-cxx4-feedstock/pull/38",
 "id": 791290323,
 "labels": [
  {
   "color": "191970",
   "default": false,
   "description": "Instruct the bot to retry the PR",
   "id": 1395367593,
   "name": "bot-rerun",
   "node_id": "MDU6TGFiZWwxMzk1MzY3NTkz",
   "url": "https://api.github.com/repos/conda-forge/netcdf-cxx4-feedstock/labels/bot-rerun"
  },
  {
   "color": "191970",
   "default": false,
   "description": "Instruct the bot to retry the PR",
   "id": 1,
   "name": "bot-rerun",
   "node_id": "hello",
   "url": "world"
  }
 ],
 "mergeable": false,
 "mergeable_state": "dirty",
 "merged": false,
 "merged_at": null,
 "number": 38,
 "state": "closed",
 "updated_at": "2021-12-06T18:01:56Z"
}