{
 "ETag": "W/\"f5361c91fdb10b81f1b167cc0fc71ff9a77a53fc71336478c9c6c3f852baf0be\"",
 "Last-Modified": "Thu, 12 Oct 2023 00:27:23 GMT",
 "base": {
  "repo": {
   "name": "sweets-feedstock"
  }
 },
 "closed_at": null,
 "created_at": "2023-10-12T00:27:18Z",
 "draft": false,
 "head": {
  "ref": "0.2.2_h251976"
 },
 "html_url": "https://github.com/conda-forge/sweets-feedstock/pull/3",
 "id": 1553229043,
 "labels": [],
 "mergeable": true,
 "mergeable_state": "unstable",
 "merged": false,
 "merged_at": null,
 "number": 3,
 "state": "open",
 "updated_at": "2023-10-12T00:27:23Z"
}