{
 "ETag": "W/\"1a280ba5a028b3014117b6539ae05669717f98376495d318a6db84e3543d9cfb\"",
 "Last-Modified": "Mon, 16 May 2022 06:53:00 GMT",
 "base": {
  "repo": {
   "name": "pyqtads-feedstock"
  }
 },
 "closed_at": "2022-05-16T06:53:00Z",
 "created_at": "2021-12-06T12:02:23Z",
 "draft": false,
 "head": {
  "ref": "3.8.1_h1fa9e0"
 },
 "html_url": "https://github.com/conda-forge/pyqtads-feedstock/pull/40",
 "id": 795811960,
 "labels": [],
 "mergeable": null,
 "mergeable_state": "unknown",
 "merged": false,
 "merged_at": null,
 "number": 40,
 "state": "closed",
 "updated_at": "2022-05-16T06:53:00Z"
}