{
 "ETag": "W/\"56dc152a0a00b72868e18fc38a6968ad28071fc341469b100ef5ed4b8d17bc2b\"",
 "Last-Modified": "Mon, 15 Jan 2024 21:26:14 GMT",
 "base": {
  "repo": {
   "name": "r-psychtools-feedstock"
  }
 },
 "closed_at": "2024-01-15T21:26:09Z",
 "created_at": "2024-01-15T21:20:02Z",
 "draft": false,
 "head": {
  "ref": "this_is_not_a_branch"
 },
 "html_url": "https://github.com/conda-forge/r-psychtools-feedstock/pull/12",
 "id": 1679837687,
 "labels": [],
 "mergeable": null,
 "mergeable_state": "unknown",
 "merged": true,
 "merged_at": "2024-01-15T21:26:09Z",
 "number": 12,
 "state": "closed",
 "updated_at": "2024-01-15T21:26:14Z"
}