{
 "ETag": "W/\"a6b66b1959f6cc26c7f1540dafbaef45d080258073ad25df75cdac34a5915d71\"",
 "Last-Modified": "Sun, 07 Aug 2022 20:45:39 GMT",
 "base": {
  "repo": {
   "name": "three.js-feedstock"
  }
 },
 "closed_at": "2022-08-07T20:45:37Z",
 "created_at": "2021-06-30T13:31:46Z",
 "draft": false,
 "head": {
  "ref": "130_hc68510"
 },
 "html_url": "https://github.com/conda-forge/three.js-feedstock/pull/27",
 "id": 680880301,
 "labels": [
  {
   "color": "191970",
   "default": false,
   "description": "Instruct the bot to retry the PR",
   "id": 1,
   "name": "bot-rerun",
   "node_id": "hello",
   "url": "world"
  }
 ],
 "mergeable": false,
 "mergeable_state": "dirty",
 "merged": false,
 "merged_at": null,
 "number": 27,
 "state": "closed",
 "updated_at": "2022-08-07T20:45:39Z"
}