{
 "builtin": {},
 "questionable": {
  "PyQt4.QtGui": {
   "__set__": true,
   "elements": [
    "pyqt"
   ]
  },
  "h5py": {
   "__set__": true,
   "elements": [
    "h5py"
   ]
  },
  "matplotlib.cm": {
   "__set__": true,
   "elements": [
    "matplotlib",
    "matplotlib-base"
   ]
  },
  "matplotlib.pyplot": {
   "__set__": true,
   "elements": [
    "matplotlib",
    "matplotlib-base"
   ]
  },
  "networkx": {
   "__set__": true,
   "elements": [
    "networkx"
   ]
  },
  "progressbar": {
   "__set__": true,
   "elements": [
    "progressbar",
    "progressbar2",
    "progressbar33"
   ]
  },
  "pylab": {
   "__set__": true,
   "elements": [
    "matplotlib",
    "matplotlib-base"
   ]
  },
  "skimage.io": {
   "__set__": true,
   "elements": [
    "scikit-image"
   ]
  },
  "vigra": {
   "__set__": true,
   "elements": [
    "vigra"
   ]
  }
 },
 "questionable no match": {},
 "required": {
  "h5py": {
   "__set__": true,
   "elements": [
    "h5py"
   ]
  },
  "matplotlib.colors": {
   "__set__": true,
   "elements": [
    "matplotlib",
    "matplotlib-base"
   ]
  },
  "matplotlib.pyplot": {
   "__set__": true,
   "elements": [
    "matplotlib",
    "matplotlib-base"
   ]
  },
  "numpy": {
   "__set__": true,
   "elements": [
    "autovizwidget",
    "inkscape",
    "numcodecs",
    "numpy"
   ]
  },
  "pylab": {
   "__set__": true,
   "elements": [
    "matplotlib",
    "matplotlib-base"
   ]
  },
  "scipy": {
   "__set__": true,
   "elements": [
    "pyamg",
    "scipy"
   ]
  },
  "scipy.misc": {
   "__set__": true,
   "elements": [
    "pyamg",
    "scipy"
   ]
  },
  "scipy.ndimage": {
   "__set__": true,
   "elements": [
    "pyamg",
    "scipy"
   ]
  },
  "scipy.ndimage.filters": {
   "__set__": true,
   "elements": [
    "pyamg",
    "scipy"
   ]
  },
  "skimage.feature": {
   "__set__": true,
   "elements": [
    "scikit-image"
   ]
  },
  "skimage.filters": {
   "__set__": true,
   "elements": [
    "scikit-image"
   ]
  },
  "skimage.io": {
   "__set__": true,
   "elements": [
    "scikit-image"
   ]
  },
  "skimage.morphology": {
   "__set__": true,
   "elements": [
    "scikit-image"
   ]
  },
  "skimage.segmentation": {
   "__set__": true,
   "elements": [
    "scikit-image"
   ]
  },
  "skimage.transform": {
   "__set__": true,
   "elements": [
    "scikit-image"
   ]
  },
  "vigra": {
   "__set__": true,
   "elements": [
    "vigra"
   ]
  },
  "z5py": {
   "__set__": true,
   "elements": [
    "z5py"
   ]
  }
 },
 "required no match": {}
}