{
 "ETag": "W/\"6a8c64e538df1dea96600482675494b6f6ce1f519d7b80016df3b0cd8dba7143\"",
 "Last-Modified": "Tue, 20 Jul 2021 08:33:40 GMT",
 "base": {
  "repo": {
   "name": "vega-cli-feedstock"
  }
 },
 "closed_at": "2021-07-20T08:33:39Z",
 "created_at": "2021-07-16T15:17:58Z",
 "draft": false,
 "head": {
  "ref": "rebuild-nodejs16-0-1_h5eb558"
 },
 "html_url": "https://github.com/conda-forge/vega-cli-feedstock/pull/12",
 "id": 691568076,
 "labels": [
  {
   "color": "191970",
   "default": false,
   "description": "Instruct the bot to retry the PR",
   "id": 1891424352,
   "name": "bot-rerun",
   "node_id": "MDU6TGFiZWwxODkxNDI0MzUy",
   "url": "https://api.github.com/repos/conda-forge/vega-cli-feedstock/labels/bot-rerun"
  }
 ],
 "mergeable": true,
 "mergeable_state": "clean",
 "merged": false,
 "merged_at": null,
 "number": 12,
 "state": "closed",
 "updated_at": "2021-07-20T08:33:40Z"
}