{
 "ETag": "W/\"9a9f6d2cb8207b1c55db7c5907a5774e302efe4b5b135966da23b08d9085aaee\"",
 "Last-Modified": "Tue, 02 May 2023 22:20:23 GMT",
 "base": {
  "repo": {
   "name": "activitysim-feedstock"
  }
 },
 "closed_at": "2023-05-02T22:20:23Z",
 "created_at": "2023-04-17T22:23:02Z",
 "draft": false,
 "head": {
  "ref": "this_is_not_a_branch"
 },
 "html_url": "https://github.com/conda-forge/activitysim-feedstock/pull/12",
 "id": 1317412961,
 "labels": [],
 "mergeable": null,
 "mergeable_state": "unknown",
 "merged": true,
 "merged_at": "2023-05-02T22:20:22Z",
 "number": 12,
 "state": "closed",
 "updated_at": "2023-05-02T22:20:23Z"
}