{
 "ETag": "W/\"f9f95caac559fdc8d3035a24ca1fe49cb3b8d92966a8c2817093fe89a78decbd\"",
 "Last-Modified": "Sat, 05 Feb 2022 16:24:02 GMT",
 "base": {
  "repo": {
   "name": "r-quantreg-feedstock"
  }
 },
 "closed_at": "2022-02-05T16:24:02Z",
 "created_at": "2022-01-26T20:59:10Z",
 "draft": false,
 "head": {
  "ref": "5.87_h3eeee6"
 },
 "html_url": "https://github.com/conda-forge/r-quantreg-feedstock/pull/30",
 "id": 832806430,
 "labels": [],
 "mergeable": null,
 "mergeable_state": "unknown",
 "merged": false,
 "merged_at": null,
 "number": 30,
 "state": "closed",
 "updated_at": "2022-02-05T16:24:02Z"
}