{
 "ETag": "W/\"d245bdcdaa9149e45b7ba41d6dd31985380a9289b09b1777c3a53e4731b7c8f0\"",
 "Last-Modified": "Wed, 19 Apr 2023 16:12:10 GMT",
 "base": {
  "repo": {
   "name": "python-sounddevice-feedstock"
  }
 },
 "closed_at": "2023-04-19T16:12:10Z",
 "created_at": "2021-07-18T13:39:48Z",
 "draft": false,
 "head": {
  "ref": "0.4.2_h356c6e"
 },
 "html_url": "https://github.com/conda-forge/python-sounddevice-feedstock/pull/11",
 "id": 692090876,
 "labels": [
  {
   "color": "191970",
   "default": false,
   "description": "Instruct the bot to retry the PR",
   "id": 1891175325,
   "name": "bot-rerun",
   "node_id": "MDU6TGFiZWwxODkxMTc1MzI1",
   "url": "https://api.github.com/repos/conda-forge/python-sounddevice-feedstock/labels/bot-rerun"
  },
  {
   "color": "191970",
   "default": false,
   "description": "Instruct the bot to retry the PR",
   "id": 1,
   "name": "bot-rerun",
   "node_id": "hello",
   "url": "world"
  }
 ],
 "mergeable": false,
 "mergeable_state": "dirty",
 "merged": false,
 "merged_at": null,
 "number": 11,
 "state": "closed",
 "updated_at": "2023-04-19T16:12:10Z"
}