{
 "ETag": "W/\"5727a15f49b04aa7478ea1645e8466065f5a0ac44f471b4a0a66daa51a067900\"",
 "Last-Modified": "Mon, 07 Feb 2022 20:28:27 GMT",
 "base": {
  "repo": {
   "name": "r-duckdb-feedstock"
  }
 },
 "closed_at": "2022-02-07T20:28:27Z",
 "created_at": "2022-02-07T19:47:45Z",
 "draft": false,
 "head": {
  "ref": "this_is_not_a_branch"
 },
 "html_url": "https://github.com/conda-forge/r-duckdb-feedstock/pull/9",
 "id": 842102598,
 "labels": [],
 "mergeable": null,
 "mergeable_state": "unknown",
 "merged": true,
 "merged_at": "2022-02-07T20:28:27Z",
 "number": 9,
 "state": "closed",
 "updated_at": "2022-02-07T20:28:27Z"
}