{
 "ETag": "W/\"72bb9a5e42d4a4ba8a11cf2da1492b4120e72ab08ff4de73e28c70b1b2d39945\"",
 "Last-Modified": "Mon, 15 Jan 2024 21:19:20 GMT",
 "base": {
  "repo": {
   "name": "starfile-feedstock"
  }
 },
 "closed_at": null,
 "created_at": "2024-01-15T21:19:12Z",
 "draft": false,
 "head": {
  "ref": "0.5.3_h7aea2f"
 },
 "html_url": "https://github.com/conda-forge/starfile-feedstock/pull/5",
 "id": 1679836971,
 "labels": [],
 "mergeable": true,
 "mergeable_state": "clean",
 "merged": false,
 "merged_at": null,
 "number": 5,
 "state": "open",
 "updated_at": "2024-01-15T21:19:20Z"
}