{
 "ETag": "W/\"bd05fa790312c67b289594971a3ce615\"",
 "Last-Modified": "Mon, 10 Aug 2020 18:17:14 GMT",
 "base": {
  "repo": {
   "name": "speechrecognition-feedstock"
  }
 },
 "closed_at": "2020-08-10T18:17:13Z",
 "created_at": "2018-07-07T04:12:07Z",
 "draft": false,
 "head": {
  "ref": "noarch_migration"
 },
 "html_url": "https://github.com/conda-forge/speechrecognition-feedstock/pull/7",
 "id": 199879313,
 "labels": [
  {
   "color": "191970",
   "default": false,
   "description": "Instruct the bot to retry the PR",
   "id": 1,
   "name": "bot-rerun",
   "node_id": "hello",
   "url": "world"
  }
 ],
 "mergeable": false,
 "mergeable_state": "dirty",
 "merged": false,
 "merged_at": null,
 "number": 7,
 "state": "closed",
 "updated_at": "2020-08-10T18:17:14Z"
}