{
 "ETag": "W/\"f831ea7e6a5bdb7c32b8eb9b00fef8972af1b0363a0aab990e08b71133b968be\"",
 "Last-Modified": "Thu, 10 Feb 2022 18:00:27 GMT",
 "base": {
  "repo": {
   "name": "scikit-downscale-feedstock"
  }
 },
 "closed_at": "2022-02-10T18:00:14Z",
 "created_at": "2022-02-10T02:42:12Z",
 "draft": false,
 "head": {
  "ref": "0.1.0_h4278f4"
 },
 "html_url": "https://github.com/conda-forge/scikit-downscale-feedstock/pull/2",
 "id": 844630649,
 "labels": [],
 "mergeable": true,
 "mergeable_state": "clean",
 "merged": false,
 "merged_at": null,
 "number": 2,
 "state": "closed",
 "updated_at": "2022-02-10T18:00:27Z"
}