{
 "ETag": "W/\"bddd711e832464da80edcc817deb93873fb7eeb7f98c7cc9bdd417211f895c0d\"",
 "Last-Modified": "Sat, 19 Feb 2022 02:43:53 GMT",
 "base": {
  "repo": {
   "name": "apache-airflow-providers-oracle-feedstock"
  }
 },
 "closed_at": "2022-02-19T02:43:53Z",
 "created_at": "2022-02-18T18:28:40Z",
 "draft": false,
 "head": {
  "ref": "this_is_not_a_branch"
 },
 "html_url": "https://github.com/conda-forge/apache-airflow-providers-oracle-feedstock/pull/5",
 "id": 857482167,
 "labels": [],
 "mergeable": null,
 "mergeable_state": "unknown",
 "merged": true,
 "merged_at": "2022-02-19T02:43:53Z",
 "number": 5,
 "state": "closed",
 "updated_at": "2022-02-19T02:43:53Z"
}