{
 "ETag": "W/\"e7187529d6e4e550210bfad61b91c6091f7702bcd0efba2430f506bb797103ac\"",
 "Last-Modified": "Tue, 11 Oct 2022 19:31:37 GMT",
 "base": {
  "repo": {
   "name": "r-tfruns-feedstock"
  }
 },
 "closed_at": "2022-10-11T19:31:34Z",
 "created_at": "2022-10-11T19:26:49Z",
 "draft": false,
 "head": {
  "ref": "this_is_not_a_branch"
 },
 "html_url": "https://github.com/conda-forge/r-tfruns-feedstock/pull/8",
 "id": 1083743517,
 "labels": [],
 "mergeable": null,
 "mergeable_state": "unknown",
 "merged": true,
 "merged_at": "2022-10-11T19:31:34Z",
 "number": 8,
 "state": "closed",
 "updated_at": "2022-10-11T19:31:37Z"
}