{
 "ETag": "W/\"41d585311cb5114b5e4de46c3ea5e78c12c5e632f7b53b7e1f501606dbbe34a0\"",
 "Last-Modified": "Sat, 24 Jun 2023 21:35:29 GMT",
 "base": {
  "repo": {
   "name": "conda-forge-pinning-feedstock"
  }
 },
 "closed_at": null,
 "created_at": "2023-06-24T21:35:25Z",
 "draft": false,
 "head": {
  "ref": "new_pin-openturns-1.21-0-_he235e6"
 },
 "html_url": "https://github.com/conda-forge/conda-forge-pinning-feedstock/pull/4599",
 "id": 1406361985,
 "labels": [],
 "mergeable": true,
 "mergeable_state": "clean",
 "merged": false,
 "merged_at": null,
 "number": 4599,
 "state": "open",
 "updated_at": "2023-06-24T21:35:29Z"
}