{
 "ETag": "W/\"b49d2df5241337ea1d23c97f6a825a6a\"",
 "Last-Modified": "Sun, 03 Nov 2019 16:20:38 GMT",
 "base": {
  "repo": {
   "name": "rdflib-feedstock"
  }
 },
 "closed_at": "2019-11-03T16:20:38Z",
 "created_at": "2019-11-03T15:25:35Z",
 "head": {
  "ref": "rebuild-python3801"
 },
 "html_url": "https://github.com/conda-forge/rdflib-feedstock/pull/4",
 "id": 336036949,
 "labels": [],
 "mergeable": null,
 "mergeable_state": "unknown",
 "merged": true,
 "merged_at": "2019-11-03T16:20:37Z",
 "number": 4,
 "state": "closed",
 "updated_at": "2019-11-03T16:20:38Z"
}