{
 "ETag": "W/\"a8b4a80e55a6867132f48b9507ec9a4c\"",
 "Last-Modified": "Sat, 22 Feb 2020 08:35:54 GMT",
 "base": {
  "repo": {
   "name": "intel-compute-runtime-feedstock"
  }
 },
 "closed_at": "2020-02-22T08:35:54Z",
 "created_at": "2020-01-24T14:19:56Z",
 "head": {
  "ref": "20.03.15346"
 },
 "html_url": "https://github.com/conda-forge/intel-compute-runtime-feedstock/pull/15",
 "id": 366858630,
 "labels": [],
 "mergeable": null,
 "mergeable_state": "unknown",
 "merged": false,
 "merged_at": null,
 "number": 15,
 "state": "closed",
 "updated_at": "2020-02-22T08:35:54Z"
}