{
 "ETag": "W/\"6f6abc39dc8ddd6b23e0b5110c8dd70788e5c66ea7718f6c403e5fffa6aca35e\"",
 "Last-Modified": "Wed, 19 Apr 2023 05:25:40 GMT",
 "base": {
  "repo": {
   "name": "pyannote.database-feedstock"
  }
 },
 "closed_at": "2023-04-19T05:25:40Z",
 "created_at": "2023-03-27T15:52:59Z",
 "draft": false,
 "head": {
  "ref": "5.0.0_hed78c8"
 },
 "html_url": "https://github.com/conda-forge/pyannote.database-feedstock/pull/10",
 "id": 1291604576,
 "labels": [],
 "mergeable": false,
 "mergeable_state": "dirty",
 "merged": false,
 "merged_at": null,
 "number": 10,
 "state": "closed",
 "updated_at": "2023-04-19T05:25:40Z"
}