{
 "ETag": "W/\"58ad72952b39e9b51272e17a873f0ed5\"",
 "Last-Modified": "Mon, 16 Dec 2019 15:44:33 GMT",
 "base": {
  "repo": {
   "name": "radical.pilot-feedstock"
  }
 },
 "closed_at": "2019-12-16T15:44:33Z",
 "created_at": "2019-12-12T18:17:14Z",
 "head": {
  "ref": "0.90.8"
 },
 "html_url": "https://github.com/conda-forge/radical.pilot-feedstock/pull/42",
 "id": 352547479,
 "labels": [],
 "mergeable": true,
 "mergeable_state": "unstable",
 "merged": false,
 "merged_at": null,
 "number": 42,
 "state": "closed",
 "updated_at": "2019-12-16T15:44:33Z"
}