{
 "ETag": "W/\"f801c1cd4cdb1b4e31fdc985640bbc6e874a048ea06fdf6e2fd956d7f483fd54\"",
 "Last-Modified": "Fri, 12 Feb 2021 00:38:50 GMT",
 "base": {
  "repo": {
   "name": "asteval-feedstock"
  }
 },
 "closed_at": "2021-02-12T00:38:50Z",
 "created_at": "2021-02-12T00:26:21Z",
 "draft": false,
 "head": {
  "ref": "0.9.22_h2459f6"
 },
 "html_url": "https://github.com/conda-forge/asteval-feedstock/pull/19",
 "id": 572202215,
 "labels": [],
 "mergeable": false,
 "mergeable_state": "dirty",
 "merged": false,
 "merged_at": null,
 "number": 19,
 "state": "closed",
 "updated_at": "2021-02-12T00:38:50Z"
}