{
 "ETag": "W/\"eaa2aaf434814ed54da9a6c96b0f273748723d26e59d3022653e9c819b93df6e\"",
 "Last-Modified": "Mon, 15 Jan 2024 23:55:07 GMT",
 "base": {
  "repo": {
   "name": "ultralytics-feedstock"
  }
 },
 "closed_at": "2024-01-15T23:55:07Z",
 "created_at": "2024-01-12T17:05:59Z",
 "draft": false,
 "head": {
  "ref": "8.1.1_h922994"
 },
 "html_url": "https://github.com/conda-forge/ultralytics-feedstock/pull/144",
 "id": 1676881946,
 "labels": [],
 "mergeable": null,
 "mergeable_state": "unknown",
 "merged": false,
 "merged_at": null,
 "number": 144,
 "state": "closed",
 "updated_at": "2024-01-15T23:55:07Z"
}