{
 "ETag": "W/\"d7142b4c3294c64767a3620baa8a6c2ecbb6e452b3347562d2afc61ef4decf79\"",
 "Last-Modified": "Mon, 23 Aug 2021 01:30:55 GMT",
 "base": {
  "repo": {
   "name": "modin-feedstock"
  }
 },
 "closed_at": "2021-08-23T01:30:55Z",
 "created_at": "2021-08-21T04:14:19Z",
 "draft": false,
 "head": {
  "ref": "this_is_not_a_branch"
 },
 "html_url": "https://github.com/conda-forge/modin-feedstock/pull/19",
 "id": 717087337,
 "labels": [],
 "mergeable": null,
 "mergeable_state": "unknown",
 "merged": true,
 "merged_at": "2021-08-23T01:30:54Z",
 "number": 19,
 "state": "closed",
 "updated_at": "2021-08-23T01:30:55Z"
}